finderivatives/__init__.py
finderivatives/derivative.py
finderivatives-0.1.1.dist-info/LICENCE.txt
finderivatives-0.1.1.dist-info/METADATA
finderivatives-0.1.1.dist-info/WHEEL
finderivatives-0.1.1.dist-info/top_level.txt
finderivatives-0.1.1.dist-info/RECORD
