Metadata-Version: 2.1
Name: finderivatives
Version: 0.1.1
Summary: Library for Financial Derivatives
Home-page: 
Author: Daniel Chaparro
Author-email: daniel.chaparro.ds@gmail.com
License-File: LICENCE.txt
